kreuzberg/__init__.py
kreuzberg/__main__.py
kreuzberg/_chunker.py
kreuzberg/_config.py
kreuzberg/_constants.py
kreuzberg/_document_classification.py
kreuzberg/_entity_extraction.py
kreuzberg/_gmft.py
kreuzberg/_language_detection.py
kreuzberg/_mime_types.py
kreuzberg/_playa.py
kreuzberg/_registry.py
kreuzberg/_types.py
kreuzberg/cli.py
kreuzberg/exceptions.py
kreuzberg/extraction.py
kreuzberg/py.typed
mseep_kreuzberg-3.13.5.dist-info/licenses/LICENSE
mseep_kreuzberg-3.13.5.dist-info/METADATA
mseep_kreuzberg-3.13.5.dist-info/WHEEL
mseep_kreuzberg-3.13.5.dist-info/entry_points.txt
mseep_kreuzberg-3.13.5.dist-info/top_level.txt
mseep_kreuzberg-3.13.5.dist-info/RECORD
